[
  {
    "title": "Next Century Partners",
    "slug": "next-century-partners",
    "bio": "Next Century Partners, LLC was formed by Michael Rosenfeld, founder and CEO of Woodridge Capital Partners, LLC and a recognized leader in the real estate industry for over 30 years.   Woodridge is a Los Angeles-based real estate company that owns and develops a broad range of hotel, resort, residential, and commercial properties.  Some of the firm’s notable properties have included The Fairmont San Francisco Hotel, the InterContinental Mark Hopkins in San Francisco, Hotel Californian in Santa Barbara, and the Ritz-Carlton Kapalua.",
    "images": [
      {
        "source": "fairmont-san-francisco-exterior",
        "span": [
          10,
          6
        ]
      },
      {
        "source": "fairmont-san-francisco-lobby",
        "span": [
          6,
          4
        ]
      },
      {
        "source": "the-carlyle",
        "span": [
          5,
          3
        ]
      },
      {
        "source": "ritz-carlton-kapalua-ocean",
        "span": [
          6,
          4
        ]
      },
      {
        "source": "ritz-carlton-kapalua-pool",
        "span": [
          6,
          4
        ]
      },
      {
        "source": "hotel-californian-exterior",
        "span": [
          10,
          6
        ]
      },
      {
        "source": "hotel-californian-interior",
        "span": [
          6,
          4
        ]
      },
      {
        "source": "century-plaza-aerial",
        "span": [
          6,
          4
        ]
      }
    ]
  },
  {
    "title": "Fairmont Hotels & Resorts",
    "slug": "fairmont-hotels-resorts",
    "bio": "Fairmont Hotels & Resorts, part of AccorHotels, connects guests to the very best of its destinations worldwide, providing travelers with memorable travel experiences, thoughtful and attentive service and luxury hotels that are truly unforgettable. Each Fairmont property reflects the locale’s energy, culture and history through locally inspired cuisine, spirited bars and lounges and distinctive design and decor. With more than 70 hotels globally, and more in development, the collection boasts some of the most iconic hotels in the world.",
    "images": [
      {
        "source": "the-plaza-hotel-nyc",
        "span": [
          10,
          6
        ]
      },
      {
        "source": "the-savoy-london",
        "span": [
          10,
          6
        ]
      },
      {
        "source": "fairmont-san-francisco-exterior",
        "span": [
          10,
          6
        ]
      },
      {
        "source": "fairmont-san-francisco-penthouse",
        "span": [
          10,
          6
        ]
      },
      {
        "source": "peace-hotel-shanghai",
        "span": [
          10,
          6
        ]
      },
      {
        "source": "chateau-frontenac-quebec",
        "span": [
          10,
          6
        ]
      },
      {
        "source": "pacific-rim-vancouver-exterior",
        "span": [
          10,
          6
        ]
      },
      {
        "source": "pacific-rim-vancouver-suite",
        "span": [
          10,
          6
        ]
      }
    ]
  },
  {
    "title": "Pei Cobb Freed & Partners",
    "slug": "pei-cobb-freed-partners",
    "bio": "With projects in progress in North America, Europe, the Middle East, Asia, and Australia, Pei Cobb Freed & Partners is a leader in architectural design and sustainability. Across six decades of exceptionally diverse practice, the firm has completed building and planning projects in more than 100 cities around the world and has been recognized with more than 200 major design awards, including 24 AIA National Honor Awards.",
    "images": [
      {
        "source": "the-louvre-paris",
        "span": [
          10,
          6
        ]
      },
      {
        "source": "bank-of-china-hong-kong",
        "span": [
          10,
          6
        ]
      },
      {
        "source": "torre-espacio-madrid",
        "span": [
          10,
          6
        ]
      },
      {
        "source": "the-ellipse-360-tai-pei",
        "span": [
          10,
          6
        ]
      },
      {
        "source": "us-bank-tower-los-angeles",
        "span": [
          10,
          6
        ]
      },
      {
        "source": "7-bryant-park-new-york",
        "span": [
          10,
          6
        ]
      },
      {
        "source": "fountain-place-dallas",
        "span": [
          10,
          6
        ]
      },
      {
        "source": "first-international-bank-of-israel-tel-aviv",
        "span": [
          10,
          6
        ]
      }
    ]
  },
  {
    "title": "Yabu Pushelberg",
    "slug": "yabu-pushelberg",
    "bio": "Founded in 1980 by George Yabu and Glenn Pushelberg, Yabu Pushelberg is now one of the most recognized design firms worldwide.<br/><br/>The firm’s multidisciplinary approach is informed by an endless curiosity and driven by partnerships with thoughtful, creative like-minded people. Evolving to encompass all aspects of design, each new venture reflects an edited approach that shifts between the rational and the intuitive.<br/><br/>With studios in Toronto and New York and current projects in over sixteen countries, attention to detail and a spirit of exploration remain a hallmark of the firm.",
    "images": [
      {
        "source": "park-hyatt-new-york-lobby",
        "span": [
          10,
          6
        ]
      },
      {
        "source": "park-hyatt-new-york-pool",
        "span": [
          10,
          6
        ]
      },
      {
        "source": "four-seasons-new-york-suite",
        "span": [
          10,
          6
        ]
      },
      {
        "source": "ohori-park-residences-japan-lobby",
        "span": [
          10,
          6
        ]
      },
      {
        "source": "parkland-toronto-lounge",
        "span": [
          10,
          6
        ]
      },
      {
        "source": "parkland-toronto-master-bath",
        "span": [
          10,
          6
        ]
      },
      {
        "source": "waldorf-astoria-beijing-dining",
        "span": [
          10,
          6
        ]
      },
      {
        "source": "waldorf-astoria-beijing-stair",
        "span": [
          10,
          6
        ]
      }
    ]
  },
  {
    "title": "Marmol Radziner",
    "slug": "marmol-radziner",
    "bio": "Marmol Radziner, formed in 1989 by Leo Marmol, FAIA, and Ron Radziner, FAIA, is an established leader in the modern architectural restoration of both private and public buildings. Their recent work, including Richard Neutra’s Kronish House and E. Stewart Williams’ Santa Fe Federal Savings and Loan—now the Palm Springs Art Museum’s Architecture and Design Center—have garnered awards from the California Preservation Foundation, the State Office of Historic Preservation and California State Parks, and Docomomo US.",
    "images": [
      {
        "source": "neutra-kaufmann-house-palm-springs-pool",
        "span": [
          10,
          6
        ]
      },
      {
        "source": "neutra-kaufmann-house-palm-springs-living",
        "span": [
          10,
          6
        ]
      },
      {
        "source": "summitridge-beverly-hills-pool",
        "span": [
          10,
          6
        ]
      },
      {
        "source": "summitridge-beverly-hills-entrance",
        "span": [
          10,
          6
        ]
      },
      {
        "source": "james-perse-malibu",
        "span": [
          10,
          6
        ]
      },
      {
        "source": "palm-springs-art-museum",
        "span": [
          10,
          6
        ]
      },
      {
        "source": "ward-los-angeles",
        "span": [
          10,
          6
        ]
      },
      {
        "source": "the-accelerated-school-los-angeles",
        "span": [
          10,
          6
        ]
      }
    ]
  },
  {
    "title": "Gensler",
    "slug": "gensler",
    "bio": "Gensler is a global architecture, design and planning firm with 44 locations and more than 5,000 professionals networked across Asia, Europe, Australia, the Middle East and the Americas. Founded in 1965, the firm serves more than 3,500 active clients in virtually every industry. Gensler designers strive to make the places people live, work and play more inspiring, more resilient and more impactful.",
    "images": [
      {
        "source": "westin-denver-international-airport",
        "span": [
          10,
          6
        ]
      },
      {
        "source": "shanghai-tower-china",
        "span": [
          10,
          6
        ]
      },
      {
        "source": "ritz-carlton-jw-marriott-lalive-los-angeles",
        "span": [
          10,
          6
        ]
      },
      {
        "source": "banc-of-california-stadium-los-angeles",
        "span": [
          10,
          6
        ]
      },
      {
        "source": "the-tower-pnc-plaza-pittsburgh",
        "span": [
          10,
          6
        ]
      },
      {
        "source": "jackson-hole-airport-terminal-wyoming",
        "span": [
          10,
          6
        ]
      },
      {
        "source": "hyundai-card-air-lounge-south-korea",
        "span": [
          10,
          6
        ]
      },
      {
        "source": "two-thousand-avenue-of-the-stars-los-angeles",
        "span": [
          10,
          6
        ]
      }
    ]
  },
  {
    "title": "Harley Ellis Devereaux",
    "slug": "harley-ellis-devereaux",
    "bio": "Harley Ellis Devereaux (HED) was founded in 1908 and is one of the few architectural firms to reach this 100-year milestone.  Their longevity has fostered experience and stability, and the over 400-person firm has developed a unique expertise in creating and documenting the myriad of details required for the comprehensive building permitting and construction drawing process. HED has also served as Executive Architects for Rick Caruso’s 15-acre mixed-use development America on Brand in Glendale, Greenland USA’s 40 and 56-story Metropolis condominium towers in downtown Los Angeles, and Woodridge Capital’s 24-story Carlyle luxury residences in Westwood.  HED has six U.S. offices in Chicago, Detroit, Los Angeles, San Diego, San Francisco and Sacramento.",
    "images": [
      {
        "source": "the-carlyle-westwood-residence",
        "span": [
          10,
          6
        ]
      },
      {
        "source": "the-carlyle-westwood-pool",
        "span": [
          10,
          6
        ]
      },
      {
        "source": "americana-at-brand-california-pool",
        "span": [
          10,
          6
        ]
      },
      {
        "source": "americana-at-brand-california-retail",
        "span": [
          10,
          6
        ]
      },
      {
        "source": "circa-los-angeles",
        "span": [
          10,
          6
        ]
      },
      {
        "source": "usc-village-los-angeles",
        "span": [
          10,
          6
        ]
      },
      {
        "source": "the-vermont-los-angeles",
        "span": [
          10,
          6
        ]
      },
      {
        "source": "metropolis-downtown-los-angeles",
        "span": [
          10,
          6
        ]
      }
    ]
  },
  {
    "title": "Rios Clementi Hale Studios",
    "slug": "rios-clementi-hale-studios",
    "bio": "Design is never without story. It connects people to each other and the world around us. Rios Clementi Hale Studios works beyond boundaries to reveal, explore, and invent designs that amplify experiences. We create singular, integrated and comprehensive solutions for a variety of design challenges. Combined, our talents comprise a wide range of professional skills including architecture, landscape architecture, urban planning and design, interior design, graphics and signage, exhibit and product design, and fashion design.",
    "images": [
      {
        "source": "private-residence-one",
        "span": [
          10,
          6
        ]
      },
      {
        "source": "private-residence-two",
        "span": [
          10,
          6
        ]
      },
      {
        "source": "private-residence-three",
        "span": [
          10,
          6
        ]
      },
      {
        "source": "private-residence-four",
        "span": [
          10,
          6
        ]
      },
      {
        "source": "private-residence-five",
        "span": [
          10,
          6
        ]
      },
      {
        "source": "private-residence-six",
        "span": [
          10,
          6
        ]
      },
      {
        "source": "grand-park-los-angeles",
        "span": [
          10,
          6
        ]
      },
      {
        "source": "private-residence-seven",
        "span": [
          10,
          6
        ]
      }
    ]
  },
  {
    "title": "Jaume Plensa",
    "slug": "jaume-plensa",
    "bio": "Jaume Plensa is one of the world's foremost sculptors, internationally celebrated with museum exhibitions and public works alike. Over thirty projects by Plensa span the globe from London to Tokyo. Based in Barcelona, the artist is renowned for creating engaging and intuitive works that speak to both the power of individual introspection and a common humanity.",
    "images": [
      {
        "source": "jaume-plensa-awilda-brazil",
        "span": [
          10,
          6
        ]
      },
      {
        "source": "jaume-plensa-crown-fountain-chicago",
        "span": [
          10,
          6
        ]
      },
      {
        "source": "jaume-plensa-poets-in-bordeaux-france",
        "span": [
          10,
          6
        ]
      },
      {
        "source": "jaume-plensa-awilda-and-laura-palm-springs",
        "span": [
          10,
          6
        ]
      },
      {
        "source": "jaume-plensa-awilda-and-irma-tennessee",
        "span": [
          10,
          6
        ]
      },
      {
        "source": "jaume-plensa-house-of-knowledge-bordeaux-france",
        "span": [
          10,
          6
        ]
      },
      {
        "source": "jaume-plensa-lou-olivia-duna",
        "span": [
          10,
          6
        ]
      },
      {
        "source": "jaume-plensa-air-water-void-germany",
        "span": [
          10,
          6
        ]
      }
    ]
  }
]